mkdocs_notion_plugin/__init__.py
mkdocs_notion_plugin/blocks.py
mkdocs_notion_plugin/commands.py
mkdocs_notion_plugin/plugin.py
mkdocs_notion_plugin-0.0.7.dist-info/LICENSE
mkdocs_notion_plugin-0.0.7.dist-info/METADATA
mkdocs_notion_plugin-0.0.7.dist-info/WHEEL
mkdocs_notion_plugin-0.0.7.dist-info/entry_points.txt
mkdocs_notion_plugin-0.0.7.dist-info/RECORD
