Metadata-Version: 2.3
Name: mkdocs_notion_plugin
Version: 0.0.7
Summary: Notion Plugin for mkdocs
Author: Robbin dev team
Author-email: fdev@robbin.com.br
Requires-Python: >=3.9,<4.0
Classifier: Programming Language :: Python :: 3
Classifier: Programming Language :: Python :: 3.9
Classifier: Programming Language :: Python :: 3.10
Classifier: Programming Language :: Python :: 3.11
Classifier: Programming Language :: Python :: 3.12
Classifier: Programming Language :: Python :: 3.13
Requires-Dist: beautifulsoup4 (>=4.12.0,<5.0.0)
Requires-Dist: click (>=8.0.0,<9.0.0)
Requires-Dist: mkdocs (>=1.5.0,<2.0.0)
Requires-Dist: notion-client (>=2.3.0,<3.0.0)
Project-URL: Documentation, https://cartaorobbin.github.io/mkdocs-notion-plugin/
Project-URL: Repository, https://github.com/cartaorobbin/mkdocs-notion-plugin
